[
    {
        "songname": "牵丝戏",
        "songid": "001e7VNQ43nv4W",
        "album": [
            "牵丝戏"
        ],
        "artist": [
            "银临",
            "Aki阿杰"
        ],
        "artistid": [
            "001axJJM4SezGt",
            "000a9Zhs0oQmMy"
        ],
        "company": "独立发行",
        "genre": "Pop",
        "lan": "国语",
        "pub_time": "2015-01-01"
    },
    {
        "songname": "山外小楼夜听雨",
        "songid": "001hoRPW23jSPU",
        "album": [
            "从小到大"
        ],
        "artist": [
            "任然"
        ],
        "artistid": [
            "00067r4p0wBDDN"
        ],
        "company": "北京千和世纪文化传播有限公司",
        "genre": "Pop",
        "lan": "国语",
        "pub_time": "2016-01-15"
    },
    {
        "songname": "断桥残雪",
        "songid": "004ENQPZ0dHaqy",
        "album": [
            "Vae新歌+精选珍藏合辑"
        ],
        "artist": [
            "许嵩"
        ],
        "artistid": [
            "000CK5xN3yZDJt"
        ],
        "company": "华宇世博",
        "genre": "Pop",
        "lan": "国语",
        "pub_time": "2007-06-02"
    },
    {
        "songname": "霜雪千年",
        "songid": "003cfHwA2qNieC",
        "album": [
            "封茗囧菌翻唱合辑"
        ],
        "artist": [
            "封茗囧菌",
            "双笙"
        ],
        "artistid": [
            "002QQzkl3o3nx1",
            "001t94rh4OpQn0"
        ],
        "lan": "国语",
        "pub_time": "2016-06-07"
    },
    {
        "songname": "长生诀",
        "songid": "001mhTL141HU8K",
        "album": [
            "长生诀"
        ],
        "artist": [
            "西瓜JUN"
        ],
        "artistid": [
            "000lRN4C4aOdtS"
        ],
        "genre": "Pop",
        "lan": "国语",
        "pub_time": "2016-08-18"
    },
    {
        "songname": "清明雨上",
        "songid": "002iKNJG1FFDyU",
        "album": [
            "Vae新歌+精选珍藏合辑"
        ],
        "artist": [
            "许嵩"
        ],
        "artistid": [
            "000CK5xN3yZDJt"
        ],
        "company": "华宇世博",
        "genre": "Pop",
        "lan": "国语",
        "pub_time": "2007-06-02"
    },
    {
        "songname": "山有木兮 (橙光《人鱼传说之长生烛》主题曲)",
        "songid": "002hmm4b1UCklk",
        "album": [
            "人鱼传说之长生烛·主题曲"
        ],
        "artist": [
            "橙光音乐",
            "伦桑"
        ],
        "artistid": [
            "000sa4tT2iEMBA",
            "000vBWTq2NYeNs"
        ],
        "company": "北京六趣网络科技有限公司",
        "genre": "Pop",
        "lan": "国语",
        "pub_time": "2016-08-12"
    },
    {
        "songname": "公子向北走 (Live)",
        "songid": "000pOH6d0fbdUq",
        "album": [
            "公子向北走(Live)"
        ],
        "artist": [
            "霈丹（浪哥）"
        ],
        "artistid": [
            "001MkfqZ2c5BH1"
        ],
        "company": "独立发行",
        "genre": "Pop",
        "lan": "国语",
        "pub_time": "2019-05-29"
    },
    {
        "songname": "典狱司 (《老九门》电视剧片尾曲)",
        "songid": "001MgF1j3afiPQ",
        "album": [
            "典狱司"
        ],
        "artist": [
            "音频怪物"
        ],
        "artistid": [
            "001O2cJY0fnmg5"
        ],
        "genre": "Pop",
        "lan": "国语",
        "pub_time": "2016-07-04"
    },
    {
        "songname": "庐州月",
        "songid": "001LuLtP1LqITK",
        "album": [
            "寻雾启示"
        ],
        "artist": [
            "许嵩"
        ],
        "artistid": [
            "000CK5xN3yZDJt"
        ],
        "company": "华宇世博",
        "genre": "Pop",
        "lan": "国语",
        "pub_time": "2010-01-06"
    },
    {
        "songname": "哪吒 (《哪吒之魔童降世》电影主题曲)",
        "songid": "002AsrO40MCS5d",
        "album": [
            "哪吒"
        ],
        "artist": [
            "GAI周延",
            "大痒痒"
        ],
        "artistid": [
            "004LV0lb4fOw89",
            "000irxpp340wvO"
        ],
        "company": "霍尔果斯彩条屋影业有限公司",
        "genre": " Rap/Hip Hop",
        "lan": "国语",
        "pub_time": "2019-07-13"
    },
    {
        "songname": "雨幕 (新天龙八部端游主题曲)",
        "songid": "001BKGVe1BctBv",
        "album": [
            "雨幕"
        ],
        "artist": [
            "许嵩"
        ],
        "artistid": [
            "000CK5xN3yZDJt"
        ],
        "company": "海蝶音乐",
        "genre": "Soundtrack",
        "lan": "国语",
        "pub_time": "2019-10-13"
    },
    {
        "songname": "故梦",
        "songid": "000xKbLI2QEKE9",
        "album": [
            "翻唱歌曲合集"
        ],
        "artist": [
            "双笙"
        ],
        "artistid": [
            "001t94rh4OpQn0"
        ],
        "genre": "Pop",
        "lan": "国语",
        "pub_time": "2016-05-13"
    },
    {
        "songname": "青城山下白素贞 (《新白娘子传奇》电视剧插曲)",
        "songid": "002awsrV0qQqJF",
        "album": [
            "青城山下白素贞"
        ],
        "artist": [
            "鞠婧祎"
        ],
        "artistid": [
            "003XXZcL1OS12F"
        ],
        "company": "丝芭文化",
        "genre": "Soundtrack",
        "lan": "国语",
        "pub_time": "2019-04-16"
    },
    {
        "songname": "棠梨煎雪",
        "songid": "000A1xry3KwdhW",
        "album": [
            "腐草为萤"
        ],
        "artist": [
            "银临"
        ],
        "artistid": [
            "001axJJM4SezGt"
        ],
        "company": "独立发行",
        "genre": "Pop",
        "lan": "国语",
        "pub_time": "2013-08-23"
    },
    {
        "songname": "九九八十一 (柔情版)",
        "songid": "004XmWlq2n1SnX",
        "album": [
            "九九八十一"
        ],
        "artist": [
            "叶洛洛",
            "西瓜JUN",
            "泥鳅Niko",
            "知性的小方块"
        ],
        "artistid": [
            "003QznRR2ry01V",
            "000lRN4C4aOdtS",
            "000pLwpw25Og4A",
            "003SRSxr0ufMKi"
        ],
        "genre": "Pop",
        "lan": "国语",
        "pub_time": "2016-07-03"
    },
    {
        "songname": "人间白首 (《狐妖小红娘·竹业篇》网络动画第88集插曲)",
        "songid": "003yM7Uc3TRo5z",
        "album": [
            "人间白首"
        ],
        "artist": [
            "呦猫UNEKO"
        ],
        "artistid": [
            "003VD9fu3Eh1q4"
        ],
        "company": "腾讯动漫",
        "lan": "国语",
        "pub_time": "2019-04-26"
    },
    {
        "songname": "采茶纪",
        "songid": "004Kxue107QgYM",
        "album": [
            "原创歌曲合集"
        ],
        "artist": [
            "双笙"
        ],
        "artistid": [
            "001t94rh4OpQn0"
        ],
        "company": "独立发行",
        "genre": "Pop",
        "lan": "国语",
        "pub_time": "2016-05-04"
    },
    {
        "songname": "山水之间",
        "songid": "003EA8522GJ7tv",
        "album": [
            "不如吃茶去"
        ],
        "artist": [
            "许嵩"
        ],
        "artistid": [
            "000CK5xN3yZDJt"
        ],
        "company": "海蝶音乐",
        "genre": "Pop",
        "lan": "国语",
        "pub_time": "2014-08-23"
    },
    {
        "songname": "千古 (《花千骨》电视剧片头曲)",
        "songid": "003HBeLJ1q4Pao",
        "album": [
            "千古"
        ],
        "artist": [
            "许嵩"
        ],
        "artistid": [
            "000CK5xN3yZDJt"
        ],
        "company": "海蝶音乐",
        "genre": "Pop",
        "lan": "国语",
        "pub_time": "2015-08-20"
    },
    {
        "songname": "牵丝戏",
        "songid": "002LZ8Iv2bBWfu",
        "album": [
            "排骨教主翻唱作品"
        ],
        "artist": [
            "排骨教主"
        ],
        "artistid": [
            "001gHQcA0AFAMZ"
        ],
        "genre": "Pop",
        "lan": "国语",
        "pub_time": "2016-05-20"
    },
    {
        "songname": "忘羡 (《魔道祖师》广播剧第二季主题曲)",
        "songid": "003u5xZe1isbDi",
        "album": [
            "忘羡"
        ],
        "artist": [
            "吾恩",
            "余夏"
        ],
        "artistid": [
            "004Q5MZa33SggC",
            "004M6vSm13wyKw"
        ],
        "company": "猫耳FM",
        "genre": "Pop",
        "lan": "国语",
        "pub_time": "2019-01-15"
    },
    {
        "songname": "卷珠帘",
        "songid": "003BXELh0qM5bI",
        "album": [
            "天韵·霍尊"
        ],
        "artist": [
            "霍尊"
        ],
        "artistid": [
            "0018bYjA4bdNNi"
        ],
        "company": "臻声文化",
        "genre": "Pop",
        "lan": "国语",
        "pub_time": "2015-05-18"
    },
    {
        "songname": "锦鲤抄",
        "songid": "00289GmS1BCkev",
        "album": [
            "腐草为萤"
        ],
        "artist": [
            "银临",
            "云の泣"
        ],
        "artistid": [
            "001axJJM4SezGt",
            "002DvjWq3Qg1we"
        ],
        "company": "独立发行",
        "genre": "Pop",
        "lan": "国语",
        "pub_time": "2013-08-23"
    },
    {
        "songname": "杏花弦外雨",
        "songid": "002yTP5F1OAXQ4",
        "album": [
            "弦上春雪"
        ],
        "artist": [
            "CRITTY",
            "司夏"
        ],
        "artistid": [
            "000OhITt3FtG7c",
            "003OKNiD0iSL36"
        ],
        "company": "北京汐音文化传媒有限公司",
        "genre": "Pop",
        "lan": "国语",
        "pub_time": "2013-05-03"
    },
    {
        "songname": "狐言",
        "songid": "000idahy2pT761",
        "album": [
            "狐言"
        ],
        "artist": [
            "河图",
            "洛天依"
        ],
        "artistid": [
            "001AkuJH2G5OJJ",
            "003ktdcg3E4kaG"
        ],
        "genre": "Pop",
        "lan": "国语",
        "pub_time": "2015-12-10"
    },
    {
        "songname": "倾尽天下",
        "songid": "003eSjmB276n6J",
        "album": [
            "河图精选"
        ],
        "artist": [
            "河图"
        ],
        "artistid": [
            "001AkuJH2G5OJJ"
        ],
        "genre": "Pop",
        "lan": "国语",
        "pub_time": "2009-12-28"
    },
    {
        "songname": "故人叹",
        "songid": "000Qs0TU1QOsoz",
        "album": [
            "排骨教主翻唱作品"
        ],
        "artist": [
            "排骨教主",
            "cv王胖子",
            "西瓜JUN"
        ],
        "artistid": [
            "001gHQcA0AFAMZ",
            "0005So1P40Ifgk",
            "000lRN4C4aOdtS"
        ],
        "genre": "Pop",
        "lan": "国语",
        "pub_time": "2016-05-20"
    },
    {
        "songname": "霜雪千年",
        "songid": "001l8o0V0Y44ZQ",
        "album": [
            "排骨教主翻唱作品"
        ],
        "artist": [
            "排骨教主"
        ],
        "artistid": [
            "001gHQcA0AFAMZ"
        ],
        "genre": "Pop",
        "lan": "国语",
        "pub_time": "2016-05-20"
    },
    {
        "songname": "小城谣 (原唱:胡碧乔HuQQ)",
        "songid": "002kicqp0EroJm",
        "album": [],
        "artist": [
            "泥鳅Niko",
            "翘课迟到少恭桑"
        ],
        "artistid": [
            "000pLwpw25Og4A",
            "000A84vX2m58lp"
        ],
        "genre": "Pop",
        "lan": "国语"
    },
    {
        "songname": "伞下铭",
        "songid": "00477nep4XmHqH",
        "album": [
            "伞下铭"
        ],
        "artist": [
            "封茗囧菌",
            "洛少爷"
        ],
        "artistid": [
            "002QQzkl3o3nx1",
            "003XmWEI1F4B4b"
        ],
        "company": "独立发行",
        "genre": "Pop",
        "lan": "国语",
        "pub_time": "2018-07-24"
    },
    {
        "songname": "盗橘令",
        "songid": "000nF4XD17fxhO",
        "album": [
            "盗橘令"
        ],
        "artist": [
            "不才",
            "云の泣",
            "银临",
            "Aki阿杰"
        ],
        "artistid": [
            "002ZJbvE1TBHMD",
            "002DvjWq3Qg1we",
            "001axJJM4SezGt",
            "000a9Zhs0oQmMy"
        ],
        "company": "独立发行",
        "lan": "国语",
        "pub_time": "2019-08-23"
    },
    {
        "songname": "绝代风华 (天下3十周年主题曲)",
        "songid": "003nNk024MU5C9",
        "album": [
            "绝代风华"
        ],
        "artist": [
            "许嵩"
        ],
        "artistid": [
            "000CK5xN3yZDJt"
        ],
        "company": "海蝶音乐",
        "genre": "Pop",
        "lan": "国语",
        "pub_time": "2018-11-22"
    },
    {
        "songname": "鱼玄机",
        "songid": "002d2eC10KX4s9",
        "album": [],
        "artist": [
            "兔裹煎蛋卷"
        ],
        "artistid": [
            "002JhXUh3z4NWo"
        ],
        "genre": "Pop",
        "lan": "国语"
    },
    {
        "songname": "千灯愿",
        "songid": "003lSIRW0lT4MJ",
        "album": [
            "千灯愿"
        ],
        "artist": [
            "艾辰"
        ],
        "artistid": [
            "000985uR2CKS2P"
        ],
        "company": "凤凰涅槃",
        "genre": "Pop",
        "lan": "国语",
        "pub_time": "2019-09-07"
    },
    {
        "songname": "眉间雪 (纯歌版)",
        "songid": "000xymkm2HIwQf",
        "album": [],
        "artist": [
            "晴愔"
        ],
        "artistid": [
            "002gEdRT1DFpd8"
        ],
        "genre": "Pop",
        "lan": "国语"
    },
    {
        "songname": "满庭芳 (《狐妖小红娘·竹业篇》网络动画片头曲)",
        "songid": "00221Zpe3xMfIx",
        "album": [
            "狐妖小红娘·竹业篇 动画原声大碟 前缘"
        ],
        "artist": [
            "Mr.mo"
        ],
        "artistid": [
            "000sVt4E3l2bEb"
        ],
        "company": "腾讯动漫",
        "lan": "国语",
        "pub_time": "2019-03-21"
    },
    {
        "songname": "红尘 (《欲·黑鸢》原创游戏ED主题曲)",
        "songid": "000yWApQ2BKqYf",
        "album": [
            "《欲·黑鸢》原声带"
        ],
        "artist": [
            "小曲儿"
        ],
        "artistid": [
            "0038UP0n2geLf2"
        ],
        "genre": "Pop",
        "lan": "国语",
        "pub_time": "2012-07-23"
    },
    {
        "songname": "戏子无情",
        "songid": "003uPbjj25yAWP",
        "album": [
            "戏子无情"
        ],
        "artist": [
            "董真",
            "双笙"
        ],
        "artistid": [
            "001mwvqv18JtGT",
            "001t94rh4OpQn0"
        ],
        "company": "北京示单文化传媒有限公司",
        "lan": "国语",
        "pub_time": "2019-04-15"
    },
    {
        "songname": "九万字 (原唱:黄诗扶)",
        "songid": "003ivQdf0rG3Z5",
        "album": [
            "九万字（Cover：黄诗扶）"
        ],
        "artist": [
            "以冬"
        ],
        "artistid": [
            "000y58BN18are3"
        ],
        "lan": "国语",
        "pub_time": "2019-07-18"
    },
    {
        "songname": "生而为匠",
        "songid": "000meu1z3HAlNu",
        "album": [
            "生而为匠"
        ],
        "artist": [
            "慕寒",
            "双笙",
            "银临",
            "吾恩",
            "子弥",
            "灰老板",
            "马里奥",
            "云の泣"
        ],
        "artistid": [
            "003QSIp92kSzDX",
            "001t94rh4OpQn0",
            "001axJJM4SezGt",
            "004Q5MZa33SggC",
            "002OmCai0wFEDi",
            "004CHaYS2C81pI",
            "000bEtpe2wLd8W",
            "002DvjWq3Qg1we"
        ],
        "company": "独立发行",
        "genre": "Other",
        "lan": "国语",
        "pub_time": "2019-02-19"
    },
    {
        "songname": "绘笔江南",
        "songid": "003JK9Ry3DVRhg",
        "album": [
            "绘笔江南"
        ],
        "artist": [
            "叶洛洛",
            "西瓜JUN",
            "泥鳅Niko",
            "知性的小方块"
        ],
        "artistid": [
            "003QznRR2ry01V",
            "000lRN4C4aOdtS",
            "000pLwpw25Og4A",
            "003SRSxr0ufMKi"
        ],
        "company": "独立发行",
        "genre": "Pop",
        "lan": "国语",
        "pub_time": "2019-01-19"
    },
    {
        "songname": "繁华唱遍（yousa ver.）",
        "songid": "003MvZ9F0PF4vc",
        "album": [
            "繁华唱遍（yousa ver.）"
        ],
        "artist": [
            "泠鸢yousa"
        ],
        "artistid": [
            "002caw8n4fioLI"
        ],
        "company": "独立发行",
        "genre": "Other",
        "lan": "国语",
        "pub_time": "2019-02-07"
    },
    {
        "songname": "风起天阑",
        "songid": "003v4s5I1qcr5t",
        "album": [
            "风起天阑"
        ],
        "artist": [
            "河图"
        ],
        "artistid": [
            "001AkuJH2G5OJJ"
        ],
        "company": "独立发行",
        "genre": "Pop",
        "lan": "国语",
        "pub_time": "2010-09-30"
    },
    {
        "songname": "瓷意千年",
        "songid": "002TM6ow0U5DW2",
        "album": [
            "瓷意千年"
        ],
        "artist": [
            "陈拾月（只有影子）",
            "云の泣",
            "封茗囧菌",
            "HITA",
            "Aki阿杰",
            "赵方婧",
            "玄觞",
            "王梓钰"
        ],
        "artistid": [
            "002xZvRi1y3oZz",
            "002DvjWq3Qg1we",
            "002QQzkl3o3nx1",
            "00345j1k0ZFXru",
            "000a9Zhs0oQmMy",
            "001xruwk2A0Vw7",
            "0011C4aN0Es0ZU",
            "004WPeqa0SMAWf"
        ],
        "company": "独立发行",
        "genre": "Other",
        "lan": "国语",
        "pub_time": "2019-06-03"
    },
    {
        "songname": "长生诀 (原唱: 西瓜JUN)",
        "songid": "0042w6Bu1gAdB1",
        "album": [
            "排骨节操电台"
        ],
        "artist": [
            "排骨教主"
        ],
        "artistid": [
            "001gHQcA0AFAMZ"
        ],
        "genre": "",
        "lan": "国语",
        "pub_time": "2017-03-10"
    },
    {
        "songname": "遇萤",
        "songid": "000SfcIA34yrE3",
        "album": [
            "遇萤"
        ],
        "artist": [
            "陈拾月（只有影子）"
        ],
        "artistid": [
            "002xZvRi1y3oZz"
        ],
        "company": "独立发行",
        "genre": "Pop",
        "lan": "国语",
        "pub_time": "2018-07-20"
    },
    {
        "songname": "桃花劫",
        "songid": "002NCRTv2ojDvS",
        "album": [
            "东栏篱歌"
        ],
        "artist": [
            "东篱"
        ],
        "artistid": [
            "002KZPwH2pyNHC"
        ],
        "genre": "Pop",
        "lan": "国语",
        "pub_time": "2009-07-09"
    },
    {
        "songname": "锦鲤抄",
        "songid": "003O5FvJ1j8UdV",
        "album": [
            "锦鲤抄"
        ],
        "artist": [
            "银临",
            "云の泣"
        ],
        "artistid": [
            "001axJJM4SezGt",
            "002DvjWq3Qg1we"
        ],
        "company": "南京米漫文化传媒有限责任公司",
        "lan": "国语",
        "pub_time": "2013-04-09"
    },
    {
        "songname": "天下灯火",
        "songid": "001NSRY92r1TM3",
        "album": [
            "天下灯火"
        ],
        "artist": [
            "执素兮",
            "甘璐"
        ],
        "artistid": [
            "001sArBx4Gx9lP",
            "000n8XFg2nTBax"
        ],
        "company": "独立发行",
        "genre": "Pop",
        "lan": "国语",
        "pub_time": "2019-02-04"
    },
    {
        "songname": "一个好姑娘",
        "songid": "002K9qOA0ZBeRi",
        "album": [
            "一个傻语诗"
        ],
        "artist": [
            "MC语诗"
        ],
        "artistid": [
            "002HLF7x1teFbi"
        ],
        "lan": "国语",
        "pub_time": "2016-12-11"
    },
    {
        "songname": "黑白童子",
        "songid": "004GS37R16b3r5",
        "album": [
            "黑白童子"
        ],
        "artist": [
            "封茗囧菌"
        ],
        "artistid": [
            "002QQzkl3o3nx1"
        ],
        "company": "独立发行",
        "genre": "Other",
        "lan": "国语",
        "pub_time": "2019-04-25"
    },
    {
        "songname": "京津有味 (《食物语》中华食谣系列曲)",
        "songid": "003jLoXG2CaWDC",
        "album": [
            "京津有味"
        ],
        "artist": [
            "音频怪物"
        ],
        "artistid": [
            "001O2cJY0fnmg5"
        ],
        "company": "霍尔果斯巨匠传媒有限公司",
        "genre": "Pop",
        "lan": "国语",
        "pub_time": "2019-01-05"
    },
    {
        "songname": "终身误 (《红楼梦》青春版推广曲)",
        "songid": "000rWUE33TzA13",
        "album": [
            "终身误"
        ],
        "artist": [
            "双笙"
        ],
        "artistid": [
            "001t94rh4OpQn0"
        ],
        "genre": "Pop",
        "lan": "国语",
        "pub_time": "2017-03-04"
    },
    {
        "songname": "梦回诛仙 (《诛仙手游》情怀主题曲)",
        "songid": "002dvr2r0bcgz0",
        "album": [
            "梦回诛仙"
        ],
        "artist": [
            "李玉刚"
        ],
        "artistid": [
            "000Qm9wO1bcM6J"
        ],
        "company": "博轩音乐",
        "genre": "Soundtrack",
        "lan": "国语",
        "pub_time": "2019-10-24"
    },
    {
        "songname": "相思局",
        "songid": "000mZB3323EODJ",
        "album": [
            "相思局"
        ],
        "artist": [
            "音频怪物",
            "小W"
        ],
        "artistid": [
            "001O2cJY0fnmg5",
            "000DhOfS3ax8Oj"
        ],
        "genre": "Pop",
        "lan": "国语",
        "pub_time": "2011-06-05"
    },
    {
        "songname": "千秋此意",
        "songid": "000rZEqr3YX6rm",
        "album": [
            "司夏的原创作品"
        ],
        "artist": [
            "司夏"
        ],
        "artistid": [
            "003OKNiD0iSL36"
        ],
        "company": "独立发行",
        "genre": "Pop",
        "lan": "国语",
        "pub_time": "2016-05-29"
    },
    {
        "songname": "寻",
        "songid": "001fTR853QUndA",
        "album": [
            "寻"
        ],
        "artist": [
            "双笙"
        ],
        "artistid": [
            "001t94rh4OpQn0"
        ],
        "company": "北京润方铭鼎文化传媒有限公司",
        "lan": "国语",
        "pub_time": "2019-04-23"
    },
    {
        "songname": "桃花扇",
        "songid": "001fFl9O0FQVLo",
        "album": [
            "万有引力"
        ],
        "artist": [
            "汪苏泷"
        ],
        "artistid": [
            "001z2JmX09LLgL"
        ],
        "company": "大象音乐",
        "genre": "Pop",
        "lan": "国语",
        "pub_time": "2012-07-16"
    },
    {
        "songname": "南柯梦",
        "songid": "004BSJYD06rwT9",
        "album": [
            "泥鳅Niko的原创专辑"
        ],
        "artist": [
            "泥鳅Niko"
        ],
        "artistid": [
            "000pLwpw25Og4A"
        ],
        "company": "独立发行",
        "genre": "Pop",
        "lan": "国语",
        "pub_time": "2016-08-30"
    },
    {
        "songname": "谁动了我的琴弦 (Live)",
        "songid": "002C8j5B2JdkWn",
        "album": [
            "唱歌去旅行 全国巡回演唱会 北京站"
        ],
        "artist": [
            "周笔畅"
        ],
        "artistid": [
            "004HlS192u9J5g"
        ],
        "genre": "Pop",
        "lan": "国语",
        "pub_time": "2011-04-06"
    },
    {
        "songname": "别有天 (《寻仙》手游年度版本主题曲)",
        "songid": "0021EalB3zkEox",
        "album": [
            "别有天"
        ],
        "artist": [
            "排骨教主"
        ],
        "artistid": [
            "001gHQcA0AFAMZ"
        ],
        "company": "腾讯",
        "genre": "Soundtrack",
        "lan": "国语",
        "pub_time": "2017-12-26"
    },
    {
        "songname": "满城花开 (Live)",
        "songid": "002XGbpL0Z6eqi",
        "album": [
            "TF少年GO LIVE合集"
        ],
        "artist": [
            "王俊凯"
        ],
        "artistid": [
            "004E2BBy3X9xne"
        ],
        "genre": "Pop",
        "lan": "国语",
        "pub_time": "2014-01-17"
    },
    {
        "songname": "双抛桥",
        "songid": "001lz5rF4bfQpa",
        "album": [
            "曲倾天下"
        ],
        "artist": [
            "小曲儿",
            "晃儿"
        ],
        "artistid": [
            "0038UP0n2geLf2",
            "003MeDZy3wsH21"
        ],
        "genre": "Pop",
        "lan": "国语",
        "pub_time": "2013-01-01"
    },
    {
        "songname": "浮白",
        "songid": "002Sr8QA2EE6cM",
        "album": [
            "浮白"
        ],
        "artist": [
            "小魂"
        ],
        "artistid": [
            "002dKSkT1pKggC"
        ],
        "company": "独立发行",
        "genre": "Other",
        "lan": "国语",
        "pub_time": "2019-02-02"
    },
    {
        "songname": "长相忆",
        "songid": "001VkbR00G83Zj",
        "album": [
            "梅兰竹菊"
        ],
        "artist": [
            "五色石南叶",
            "慕寒",
            "Smile_小千",
            "苏郁青"
        ],
        "artistid": [
            "001Ibor44Jfa8g",
            "003QSIp92kSzDX",
            "0044RFZ64AOXH1",
            "000ZenlR1KAFb5"
        ],
        "company": "独立发行",
        "genre": "Pop",
        "lan": "国语",
        "pub_time": "2018-03-19"
    },
    {
        "songname": "姑苏",
        "songid": "0046lTw31ANGS6",
        "album": [
            "姑苏"
        ],
        "artist": [
            "少司命"
        ],
        "artistid": [
            "003yrv9B4JWX3W"
        ],
        "company": "聪明音乐",
        "genre": "Pop",
        "lan": "国语",
        "pub_time": "2016-05-16"
    },
    {
        "songname": "离骚",
        "songid": "003M9XWV1O8iLC",
        "album": [
            "翻唱合集"
        ],
        "artist": [
            "Vk",
            "罗之豪"
        ],
        "artistid": [
            "002p2Uo034oxBB",
            "003NhXGS3BUgCj"
        ],
        "company": "独立发行",
        "genre": "Pop",
        "lan": "国语",
        "pub_time": "2017-05-25"
    },
    {
        "songname": "春归了",
        "songid": "000Q5uUY0jeRrF",
        "album": [
            "春归了"
        ],
        "artist": [
            "苑舍",
            "玲楼"
        ],
        "artistid": [
            "000nOUvl3BmesM",
            "003do7b51Rw3B2"
        ],
        "lan": "国语",
        "pub_time": "2016-09-30"
    },
    {
        "songname": "四时令",
        "songid": "004blf6K0dPRrP",
        "album": [
            "梅兰竹菊"
        ],
        "artist": [
            "五色石南叶",
            "慕寒",
            "Smile_小千",
            "朱强"
        ],
        "artistid": [
            "001Ibor44Jfa8g",
            "003QSIp92kSzDX",
            "0044RFZ64AOXH1",
            "001d9vL70CHb1f"
        ],
        "company": "独立发行",
        "genre": "Pop",
        "lan": "国语",
        "pub_time": "2018-03-19"
    },
    {
        "songname": "长城之下",
        "songid": "001USkEU4Ht2iY",
        "album": [
            "长城之下"
        ],
        "artist": [
            "HITA"
        ],
        "artistid": [
            "00345j1k0ZFXru"
        ],
        "company": "独立发行",
        "genre": "Pop",
        "lan": "国语",
        "pub_time": "2019-09-03"
    },
    {
        "songname": "千年空城",
        "songid": "002VHDWf4L1C8W",
        "album": [
            "千年空城"
        ],
        "artist": [
            "东篱",
            "林清弄"
        ],
        "artistid": [
            "002KZPwH2pyNHC",
            "003sxvI61HLWTq"
        ],
        "genre": "Pop",
        "lan": "国语",
        "pub_time": "2012-08-14"
    },
    {
        "songname": "瑶琴",
        "songid": "000eHAGC2UjnQL",
        "album": [
            "瑶琴"
        ],
        "artist": [
            "少司命"
        ],
        "artistid": [
            "003yrv9B4JWX3W"
        ],
        "company": "聪明音乐",
        "genre": "Pop",
        "lan": "国语",
        "pub_time": "2016-12-02"
    },
    {
        "songname": "弦中歌",
        "songid": "002kKA6p1FAoPn",
        "album": [
            "【剑三长歌门】《弦中歌》"
        ],
        "artist": [
            "伦桑"
        ],
        "artistid": [
            "000vBWTq2NYeNs"
        ],
        "genre": "Pop",
        "lan": "国语",
        "pub_time": "2017-06-24"
    },
    {
        "songname": "御龙耀九天 (《御龙在天》游戏主题曲)",
        "songid": "001q9epP1NvWOu",
        "album": [
            "御龙在天 游戏原声带"
        ],
        "artist": [
            "周笔畅"
        ],
        "artistid": [
            "004HlS192u9J5g"
        ],
        "genre": "Pop",
        "lan": "国语",
        "pub_time": "2012-06-21"
    },
    {
        "songname": "夜宴惊梦 (《我乘白虎去》单元主题曲)",
        "songid": "004BKlFN3syIqU",
        "album": [
            "夜宴惊梦"
        ],
        "artist": [
            "戎一Neo"
        ],
        "artistid": [
            "000kkq410k5h7a"
        ],
        "company": "三米造music",
        "genre": "Soundtrack",
        "lan": "国语",
        "pub_time": "2019-08-21"
    },
    {
        "songname": "白首",
        "songid": "000PikfZ3VpMaG",
        "album": [],
        "artist": [
            "横颜君",
            "奇然"
        ],
        "artistid": [
            "00368GSc0dQLzx",
            "0008OyYh2o3RbD"
        ],
        "genre": "Pop",
        "lan": "国语"
    },
    {
        "songname": "对黄昏",
        "songid": "004SfAoA2dqq6Z",
        "album": [
            "曲倾天下"
        ],
        "artist": [
            "小曲儿"
        ],
        "artistid": [
            "0038UP0n2geLf2"
        ],
        "genre": "Pop",
        "lan": "国语",
        "pub_time": "2013-01-01"
    },
    {
        "songname": "何必诗债换酒钱",
        "songid": "0002UY7Q24wuLT",
        "album": [
            "何必诗债换酒钱"
        ],
        "artist": [
            "洛尘鞅_"
        ],
        "artistid": [
            "002hXYDa215Kod"
        ],
        "genre": "Pop",
        "lan": "国语",
        "pub_time": "2017-04-02"
    },
    {
        "songname": "十里烟波",
        "songid": "003GBfgz2H8W46",
        "album": [],
        "artist": [
            "鸦青"
        ],
        "artistid": [
            "000SiQox2dPzPO"
        ],
        "genre": "Pop",
        "lan": "国语"
    },
    {
        "songname": "云烟如梦 (橙光《进击的宫斗》主题曲)",
        "songid": "003I6vjn3v84W8",
        "album": [
            "进击的宫斗·橙光游戏主题曲"
        ],
        "artist": [
            "橙光音乐",
            "KasaYAYA"
        ],
        "artistid": [
            "000sa4tT2iEMBA",
            "000AsVUN39Yr2m"
        ],
        "company": "北京六趣网络科技有限公司",
        "genre": "Pop",
        "lan": "国语",
        "pub_time": "2016-06-03"
    },
    {
        "songname": "丹青误",
        "songid": "001VrHvN3KK594",
        "album": [
            "珠联璧合"
        ],
        "artist": [
            "五色石南叶",
            "Smile_小千"
        ],
        "artistid": [
            "001Ibor44Jfa8g",
            "0044RFZ64AOXH1"
        ],
        "genre": "Pop",
        "lan": "国语",
        "pub_time": "2013-11-07"
    },
    {
        "songname": "千帆尽 (人声本家)",
        "songid": "003gCXhf1U6hfq",
        "album": [
            "封茗囧菌原创合辑"
        ],
        "artist": [
            "封茗囧菌"
        ],
        "artistid": [
            "002QQzkl3o3nx1"
        ],
        "genre": "Pop",
        "lan": "国语",
        "pub_time": "2016-06-07"
    },
    {
        "songname": "醉 (原唱:嫣汐)",
        "songid": "004PQtnL2hWj8i",
        "album": [
            "三无Marblue（170509更新）"
        ],
        "artist": [
            "三无Marblue"
        ],
        "artistid": [
            "003GmO8G2ne8oq"
        ],
        "genre": "Pop",
        "lan": "国语",
        "pub_time": "2016-12-09"
    },
    {
        "songname": "依山观澜 (无念白版)",
        "songid": "001402YA3GI67e",
        "album": [],
        "artist": [
            "河图"
        ],
        "artistid": [
            "001AkuJH2G5OJJ"
        ],
        "genre": "Pop",
        "lan": "国语"
    },
    {
        "songname": "有莲",
        "songid": "0002lw9E4CzcPI",
        "album": [
            "有莲"
        ],
        "artist": [
            "辰小弦",
            "Winky诗[赵景旭]",
            "司夏_西国海妖",
            "黄师傅HBY"
        ],
        "artistid": [
            "000HyII14HzJ8j",
            "000aGmw90UirrR",
            "000UsRnT3H3tLI",
            "001S7QZL1PQVvl"
        ],
        "company": "独立发行",
        "genre": "Pop",
        "lan": "国语",
        "pub_time": "2018-08-28"
    },
    {
        "songname": "倾杯有酒",
        "songid": "000CJEAC3ebGMN",
        "album": [
            "倾杯有酒"
        ],
        "artist": [
            "晃儿"
        ],
        "artistid": [
            "003MeDZy3wsH21"
        ],
        "company": "独立发行",
        "genre": "Pop",
        "lan": "国语",
        "pub_time": "2017-03-03"
    },
    {
        "songname": "长留",
        "songid": "001otCGO3U4AEg",
        "album": [
            "长留"
        ],
        "artist": [
            "Momily"
        ],
        "artistid": [
            "002jun7Q0uSANQ"
        ],
        "genre": "Pop",
        "lan": "国语",
        "pub_time": "2015-06-19"
    },
    {
        "songname": "烬",
        "songid": "004YwdfK4XuC9Q",
        "album": [
            "河图精选"
        ],
        "artist": [
            "河图"
        ],
        "artistid": [
            "001AkuJH2G5OJJ"
        ],
        "company": "南京米漫文化传媒有限责任公司",
        "genre": "Pop",
        "lan": "国语",
        "pub_time": "2009-12-28"
    },
    {
        "songname": "花甲",
        "songid": "004FzyxG083P72",
        "album": [
            "无线星空二月主推歌曲"
        ],
        "artist": [
            "后弦"
        ],
        "artistid": [
            "002cUt1w0pizR1"
        ],
        "lan": "国语",
        "pub_time": "2010-02-24"
    },
    {
        "songname": "心乡我乡",
        "songid": "002q3cob1x2kgI",
        "album": [
            "义犹未尽"
        ],
        "artist": [
            "小义学长"
        ],
        "artistid": [
            "002lJ3su1OpgZc"
        ],
        "company": "独立发行",
        "genre": "Other",
        "lan": "国语",
        "pub_time": "2015-08-15"
    },
    {
        "songname": "水墨青花",
        "songid": "004VPeAL41N5Pt",
        "album": [],
        "artist": [
            "曹开挽"
        ],
        "artistid": [
            "001Brsiq3FG25O"
        ],
        "lan": "国语"
    },
    {
        "songname": "江山雪",
        "songid": "000oklxx29fzaY",
        "album": [
            "西楼听旧事"
        ],
        "artist": [
            "司夏"
        ],
        "artistid": [
            "003OKNiD0iSL36"
        ],
        "genre": "Pop",
        "lan": "国语",
        "pub_time": "2016-06-17"
    },
    {
        "songname": "黯月流光",
        "songid": "004EaYGL1e3tA4",
        "album": [],
        "artist": [
            "潇梦临"
        ],
        "artistid": [
            "001ySong059Lwy"
        ],
        "genre": "Pop",
        "lan": "国语"
    },
    {
        "songname": "夕山谣",
        "songid": "003Lrhdr107PuU",
        "album": [
            "西楼听旧事"
        ],
        "artist": [
            "司夏"
        ],
        "artistid": [
            "003OKNiD0iSL36"
        ],
        "genre": "Pop",
        "lan": "国语",
        "pub_time": "2016-06-17"
    },
    {
        "songname": "祝融",
        "songid": "001rWWfT2EW905",
        "album": [
            "绯の音"
        ],
        "artist": [
            "绯音"
        ],
        "artistid": [
            "00435i3B2JoHdb"
        ],
        "company": "独立发行",
        "lan": "国语",
        "pub_time": "2018-02-16"
    },
    {
        "songname": "如怀尺璧",
        "songid": "002vRQTq09PhUB",
        "album": [
            "西楼听旧事"
        ],
        "artist": [
            "司夏"
        ],
        "artistid": [
            "003OKNiD0iSL36"
        ],
        "genre": "Pop",
        "lan": "国语",
        "pub_time": "2016-06-17"
    },
    {
        "songname": "泸酒",
        "songid": "003GBOQQ0tDJjO",
        "album": [
            "原创集"
        ],
        "artist": [
            "小义学长"
        ],
        "artistid": [
            "002lJ3su1OpgZc"
        ],
        "genre": "Pop",
        "lan": "国语",
        "pub_time": "2016-09-10"
    },
    {
        "songname": "落霞云归",
        "songid": "001zqLiF1kUi6f",
        "album": [
            "戏玹"
        ],
        "artist": [
            "戏玹",
            "兰芽yaya"
        ],
        "artistid": [
            "0022KqTr4IFJI2",
            "003bDtfF2GE87D"
        ],
        "genre": "Pop",
        "lan": "国语",
        "pub_time": "2016-11-21"
    },
    {
        "songname": "两地书",
        "songid": "000CqKff0gDM0n",
        "album": [],
        "artist": [
            "HITA",
            "李俊然"
        ],
        "artistid": [
            "00345j1k0ZFXru",
            "003UuypV4TPQ6o"
        ],
        "genre": "Pop",
        "lan": "国语"
    },
    {
        "songname": "梦回九龙朝",
        "songid": "002yF4Zp4Dq3bJ",
        "album": [],
        "artist": [
            "华语群星"
        ],
        "artistid": [
            "000vYUqh1SqjQQ"
        ],
        "genre": "Pop",
        "lan": "国语"
    },
    {
        "songname": "铜镜吟",
        "songid": "001ghcFp3AFf0r",
        "album": [],
        "artist": [
            "钟明秋"
        ],
        "artistid": [
            "004Cyoq91y7z8H"
        ],
        "genre": "Pop",
        "lan": "国语"
    },
    {
        "songname": "月夜秋",
        "songid": "004DSuMe4CyzAW",
        "album": [],
        "artist": [
            "乌拉喵"
        ],
        "artistid": [
            "0021YBAz4IJ73N"
        ],
        "lan": "国语"
    },
    {
        "songname": "宿雨冷",
        "songid": "000zMtsn18hI4c",
        "album": [],
        "artist": [
            "老虎欧巴"
        ],
        "artistid": [
            "003OLTxD418vJm"
        ],
        "genre": "Pop",
        "lan": "国语"
    },
    {
        "songname": "与君诺",
        "songid": "000nRR7J4XwORN",
        "album": [],
        "artist": [
            "风逝"
        ],
        "artistid": [
            "0047NSI52HNwVz"
        ],
        "company": "5sing",
        "lan": "国语"
    },
    {
        "songname": "念平生",
        "songid": "001YHIPa0PAclX",
        "album": [
            "司夏的原创作品"
        ],
        "artist": [
            "司夏"
        ],
        "artistid": [
            "003OKNiD0iSL36"
        ],
        "company": "独立发行",
        "genre": "Pop",
        "lan": "国语",
        "pub_time": "2016-05-29"
    },
    {
        "songname": "连公子 (剧情版)",
        "songid": "003cUVlE38Ydtd",
        "album": [
            "文子轩"
        ],
        "artist": [
            "文子轩"
        ],
        "artistid": [
            "001FOHqv3gy7IQ"
        ],
        "genre": "Pop",
        "lan": "国语",
        "pub_time": "2016-08-12"
    },
    {
        "songname": "听风无涯",
        "songid": "0005UpnT4KvRrs",
        "album": [
            "愿娶春风笔"
        ],
        "artist": [
            "临暗iZumi",
            "伊水"
        ],
        "artistid": [
            "002704fQ3Ju52N",
            "001O2Qwh05xinJ"
        ],
        "genre": "Pop",
        "lan": "国语",
        "pub_time": "2015-01-01"
    },
    {
        "songname": "第三十八年夏至",
        "songid": "003UaBZ10T3UQB",
        "album": [
            "风起天阑"
        ],
        "artist": [
            "河图"
        ],
        "artistid": [
            "001AkuJH2G5OJJ"
        ],
        "company": "独立发行",
        "genre": "Pop",
        "lan": "国语",
        "pub_time": "2010-09-30"
    },
    {
        "songname": "望",
        "songid": "002FbySW36HH6d",
        "album": [
            "望"
        ],
        "artist": [
            "小时姑娘"
        ],
        "artistid": [
            "0047INbz4Tra3U"
        ],
        "company": "独立发行",
        "genre": "Pop",
        "lan": "国语",
        "pub_time": "2017-09-20"
    },
    {
        "songname": "归去来兮",
        "songid": "004YcNnY4ECx28",
        "album": [
            "归去来兮"
        ],
        "artist": [
            "曼殊"
        ],
        "artistid": [
            "0002cISQ3fkbIB"
        ],
        "genre": "Pop",
        "lan": "国语",
        "pub_time": "2019-07-05"
    }
]